{
  "definitions": {},
  "$schema": "http://json-schema.org/draft-07/schema#",
  "$id": "http://example.com/root.json",
  "type": "object",
  "title": "The Root Schema",
  "required": [
    "data"
  ],
  "properties": {
    "data": {
      "$id": "#/properties/data",
      "type": "object",
      "title": "The Data Schema",
      "required": [
        "id",
        "type",
        "attributes"
      ],
      "properties": {
        "id": {
          "$id": "#/properties/data/properties/id",
          "type": "string",
          "title": "The Id Schema",
          "default": "",
          "examples": [
            "2318"
          ],
          "pattern": "^(.*)$"
        },
        "type": {
          "$id": "#/properties/data/properties/type",
          "type": "string",
          "title": "The Type Schema",
          "default": "",
          "examples": [
            "account"
          ],
          "pattern": "^(.*)$"
        },
        "attributes": {
          "$id": "#/properties/data/properties/attributes",
          "type": "object",
          "title": "The Attributes Schema",
          "required": [
            "email",
            "created_at"
          ],
          "properties": {
            "email": {
              "$id": "#/properties/data/properties/attributes/properties/email",
              "type": "string",
              "title": "The Email Schema",
              "default": "",
              "examples": [
                "ernestine_ohara@nitzsche.name"
              ],
              "pattern": "^(.*)$"
            },
            "created_at": {
              "$id": "#/properties/data/properties/attributes/properties/created_at",
              "type": "string",
              "title": "The Created_at Schema",
              "default": "",
              "examples": [
                "2019-08-22T14:11:27.475Z"
              ],
              "pattern": "^(.*)$"
            }
          }
        }
      }
    }
  }
}
